livestack/__init__.py
livestack/monitor.py
livestack-0.5.0.dist-info/licenses/LICENSE
livestack-0.5.0.dist-info/METADATA
livestack-0.5.0.dist-info/WHEEL
livestack-0.5.0.dist-info/top_level.txt
livestack-0.5.0.dist-info/RECORD
