Metadata-Version: 2.4
Name: livestack
Version: 0.5.0
Summary: Live minimal inline stack display for Python scripts
Home-page: https://github.com/viljan1/LiveStack-py
License: MIT
Classifier: Programming Language :: Python :: 3
Classifier: License :: OSI Approved :: MIT License
Classifier: Operating System :: OS Independent
Requires-Python: >=3.7
License-File: LICENSE
Dynamic: classifier
Dynamic: description
Dynamic: description-content-type
Dynamic: home-page
Dynamic: license
Dynamic: license-file
Dynamic: requires-python
Dynamic: summary
